MANIFEST.in
README.rst
setup.py
qw/Sort Without Sort.py
qw/__init__.py
qw/models.py
qwe/Reverse_Int.py
qwe/__init__.py
qwer.egg-info/PKG-INFO
qwer.egg-info/SOURCES.txt
qwer.egg-info/dependency_links.txt
qwer.egg-info/requires.txt
qwer.egg-info/top_level.txt